envs/__init__.py
gym_fearbun2/__init__.py
gym_fearbun2/envs/__init__.py
gym_fearbun2/envs/random_walk/__init__.py
gym_fearbun2/envs/random_walk/random_walk.py
gym2_pkg_fearbun-0.0.1.dist-info/METADATA
gym2_pkg_fearbun-0.0.1.dist-info/WHEEL
gym2_pkg_fearbun-0.0.1.dist-info/top_level.txt
gym2_pkg_fearbun-0.0.1.dist-info/RECORD
